skmdn/__init__.py
scikit_mdn-0.0.3.dist-info/LICENSE
scikit_mdn-0.0.3.dist-info/METADATA
scikit_mdn-0.0.3.dist-info/WHEEL
scikit_mdn-0.0.3.dist-info/top_level.txt
scikit_mdn-0.0.3.dist-info/RECORD
