Metadata-Version: 2.1
Name: scikit-mdn
Version: 0.0.3
Summary: Mixture Density Networks in scikit-learn
Author: Vincent D. Warmerdam
License-File: LICENSE
Requires-Dist: numpy <2
Requires-Dist: scikit-learn
Requires-Dist: torch
Provides-Extra: dev
Requires-Dist: pytest ; extra == 'dev'
Requires-Dist: mkdocs-material ; extra == 'dev'
Requires-Dist: mkdocstrings ; extra == 'dev'
Requires-Dist: ipywidgets ; extra == 'dev'
